gisdo/__init__.py
gisdo/actions.py
gisdo/alchemy_models.py
gisdo/alchemy_session.py
gisdo/app_meta.py
gisdo/apps.py
gisdo/collector.py
gisdo/constants.py
gisdo/exceptions.py
gisdo/extensions.py
gisdo/forms.py
gisdo/logger.py
gisdo/models.py
gisdo/proxy.py
gisdo/reports.py
gisdo/runtests.py
gisdo/service.py
gisdo/settings.py
gisdo/signals.py
gisdo/tasks.py
gisdo/urls.py
gisdo/utils.py
gisdo/xml_helpers.py
gisdo/algorithm/__init__.py
gisdo/algorithm/application.py
gisdo/algorithm/base.py
gisdo/algorithm/capacities.py
gisdo/algorithm/constants.py
gisdo/algorithm/direct.py
gisdo/algorithm/enrolled.py
gisdo/algorithm/utils.py
gisdo/counter/__init__.py
gisdo/counter/age.py
gisdo/counter/base.py
gisdo/counter/constants.py
gisdo/counter/counter.py
gisdo/counter/declaration.py
gisdo/counter/filters.py
gisdo/counter/provider.py
gisdo/index/__init__.py
gisdo/index/application.py
gisdo/index/base.py
gisdo/index/capacities.py
gisdo/index/constants.py
gisdo/index/direct.py
gisdo/index/enrolled.py
gisdo/index/queue.py
gisdo/index_report/__init__.py
gisdo/index_report/collector.py
gisdo/index_report/constants.py
gisdo/index_report/forms.py
gisdo/index_report/helpers.py
gisdo/index_report/index_report.xlsx
gisdo/index_report/reports.py
gisdo/index_report/service.py
gisdo/index_report/tasks.py
gisdo/management/__init__.py
gisdo/management/commands/__init__.py
gisdo/management/commands/check_gisdo_report.py
gisdo/management/commands/gisdo_calc.py
gisdo/management/commands/synchronize_units.py
gisdo/migrations/0001_initial.py
gisdo/migrations/0002_auto_20181017_0903.py
gisdo/migrations/0003_auto_20181217_2217.py
gisdo/migrations/0004_delete_plugin_work_days.py
gisdo/migrations/0005_gisdounit_related_to_mo.py
gisdo/migrations/0006_schedulesettings_attendance_transfer_type.py
gisdo/migrations/0007_auto_20200207_1326.py
gisdo/migrations/0008_auto_20200210_1450.py
gisdo/migrations/0009_moerrorresponse.py
gisdo/migrations/0010_auto_20210425_1815.py
gisdo/migrations/0011_clean_related_mo.py
gisdo-5.3.2.46.dist-info/METADATA
gisdo-5.3.2.46.dist-info/WHEEL
gisdo-5.3.2.46.dist-info/top_level.txt
gisdo-5.3.2.46.dist-info/RECORD
